{
 "attach_print": 0,
 "channel": "Email",
 "condition": "doc.razorpayx_payout_status in [\"Cancelled\", \"Rejected\", \"Failed\", \"Reversed\"]",
 "creation": "2025-01-21 13:45:11.433147",
 "days_in_advance": 0,
 "docstatus": 0,
 "doctype": "Notification",
 "document_type": "Payment Entry",
 "enabled": 0,
 "event": "Value Change",
 "idx": 0,
 "is_standard": 1,
 "message": "<h3>Payout has been <span style=\"color: red\">{{ doc.razorpayx_payout_status }}</span></h3>\n\n<p><strong>For Payment Entry:</strong> {{ doc.name }}<br></p>\n\n<hr>\n\n<p><strong>Remarks:</strong></p>\n\n<p>{{ doc.remarks }}</p>\n",
 "message_type": "Markdown",
 "modified": "2025-01-29 12:02:01.518357",
 "modified_by": "Administrator",
 "module": "Razorpayx Integration",
 "name": "Failed Payout",
 "owner": "Administrator",
 "recipients": [
  {
   "receiver_by_document_field": "owner",
   "receiver_by_role": ""
  }
 ],
 "send_system_notification": 0,
 "send_to_all_assignees": 0,
 "sender": "",
 "sender_email": "",
 "subject": "Payout has been {{ doc.razorpayx_payout_status }} for Payment Entry {{ doc.name }}",
 "value_changed": "razorpayx_payout_status"
}